{"info": {"description": "ff_test_data", "year": 2025, "contributor": "Talen", "date_created": "2025-01-10"}, "images": [{"id": 6154796, "file_name": "6154796.jpg"}, {"id": 6154399, "file_name": "6154399.jpg"}, {"id": 6153638, "file_name": "6153638.jpg"}, {"id": 6155644, "file_name": "6155644.jpg"}, {"id": 6155463, "file_name": "6155463.jpg"}, {"id": 6154283, "file_name": "6154283.jpg"}, {"id": 6155214, "file_name": "6155214.jpg"}, {"id": 6155751, "file_name": "6155751.jpg"}, {"id": 6154090, "file_name": "6154090.jpg"}, {"id": 6154869, "file_name": "6154869.jpg"}, {"id": 6154497, "file_name": "6154497.jpg"}, {"id": 6155195, "file_name": "6155195.jpg"}, {"id": 6155770, "file_name": "6155770.jpg"}, {"id": 6153493, "file_name": "6153493.jpg"}, {"id": 6155470, "file_name": "6155470.jpg"}, {"id": 6154266, "file_name": "6154266.jpg"}, {"id": 6155311, "file_name": "6155311.jpg"}, {"id": 6153456, "file_name": "6153456.jpg"}, {"id": 6155601, "file_name": "6155601.jpg"}, {"id": 6156095, "file_name": "6156095.jpg"}, {"id": 6155439, "file_name": "6155439.jpg"}, {"id": 6155176, "file_name": "6155176.jpg"}, {"id": 6155298, "file_name": "6155298.jpg"}, {"id": 6155303, "file_name": "6155303.jpg"}, {"id": 6155008, "file_name": "6155008.jpg"}, {"id": 6155632, "file_name": "6155632.jpg"}, {"id": 6155744, "file_name": "6155744.jpg"}, {"id": 6155747, "file_name": "6155747.jpg"}, {"id": 6155450, "file_name": "6155450.jpg"}, {"id": 6154795, "file_name": "6154795.jpg"}, {"id": 6154841, "file_name": "6154841.jpg"}, {"id": 6155960, "file_name": "6155960.jpg"}, {"id": 6155434, "file_name": "6155434.jpg"}, {"id": 6153637, "file_name": "6153637.jpg"}, {"id": 6155111, "file_name": "6155111.jpg"}, {"id": 6155179, "file_name": "6155179.jpg"}, {"id": 6155425, "file_name": "6155425.jpg"}, {"id": 6154195, "file_name": "6154195.jpg"}, {"id": 6155410, "file_name": "6155410.jpg"}, {"id": 6155189, "file_name": "6155189.jpg"}, {"id": 6155321, "file_name": "6155321.jpg"}, {"id": 6155448, "file_name": "6155448.jpg"}, {"id": 6155264, "file_name": "6155264.jpg"}, {"id": 6155203, "file_name": "6155203.jpg"}, {"id": 6155599, "file_name": "6155599.jpg"}, {"id": 6155204, "file_name": "6155204.jpg"}, {"id": 6155205, "file_name": "6155205.jpg"}, {"id": 6155157, "file_name": "6155157.jpg"}, {"id": 6155740, "file_name": "6155740.jpg"}, {"id": 6154927, "file_name": "6154927.jpg"}, {"id": 6154936, "file_name": "6154936.jpg"}, {"id": 6155771, "file_name": "6155771.jpg"}, {"id": 6155443, "file_name": "6155443.jpg"}, {"id": 6154820, "file_name": "6154820.jpg"}, {"id": 6155000, "file_name": "6155000.jpg"}, {"id": 6154972, "file_name": "6154972.jpg"}, {"id": 6155743, "file_name": "6155743.jpg"}, {"id": 6155738, "file_name": "6155738.jpg"}, {"id": 6153631, "file_name": "6153631.jpg"}, {"id": 6154940, "file_name": "6154940.jpg"}, {"id": 6154077, "file_name": "6154077.jpg"}, {"id": 6153635, "file_name": "6153635.jpg"}, {"id": 6154805, "file_name": "6154805.jpg"}, {"id": 6153696, "file_name": "6153696.jpg"}, {"id": 6154390, "file_name": "6154390.jpg"}, {"id": 6154898, "file_name": "6154898.jpg"}, {"id": 6155198, "file_name": "6155198.jpg"}, {"id": 6155619, "file_name": "6155619.jpg"}, {"id": 6154975, "file_name": "6154975.jpg"}, {"id": 6154806, "file_name": "6154806.jpg"}, {"id": 6155184, "file_name": "6155184.jpg"}, {"id": 6154032, "file_name": "6154032.jpg"}, {"id": 6155469, "file_name": "6155469.jpg"}, {"id": 6153572, "file_name": "6153572.jpg"}, {"id": 6155772, "file_name": "6155772.jpg"}, {"id": 6155803, "file_name": "6155803.jpg"}, {"id": 6153491, "file_name": "6153491.jpg"}, {"id": 6154078, "file_name": "6154078.jpg"}, {"id": 6155291, "file_name": "6155291.jpg"}, {"id": 6154981, "file_name": "6154981.jpg"}, {"id": 6155183, "file_name": "6155183.jpg"}, {"id": 6156063, "file_name": "6156063.jpg"}, {"id": 6154961, "file_name": "6154961.jpg"}, {"id": 6155435, "file_name": "6155435.jpg"}, {"id": 6155442, "file_name": "6155442.jpg"}, {"id": 6155292, "file_name": "6155292.jpg"}, {"id": 6155207, "file_name": "6155207.jpg"}, {"id": 6154959, "file_name": "6154959.jpg"}, {"id": 6154398, "file_name": "6154398.jpg"}, {"id": 6154384, "file_name": "6154384.jpg"}, {"id": 6155312, "file_name": "6155312.jpg"}, {"id": 6155208, "file_name": "6155208.jpg"}, {"id": 6155246, "file_name": "6155246.jpg"}, {"id": 6155003, "file_name": "6155003.jpg"}, {"id": 6155753, "file_name": "6155753.jpg"}, {"id": 6154817, "file_name": "6154817.jpg"}, {"id": 6154803, "file_name": "6154803.jpg"}, {"id": 6155653, "file_name": "6155653.jpg"}, {"id": 6154194, "file_name": "6154194.jpg"}, {"id": 6155155, "file_name": "6155155.jpg"}, {"id": 6155830, "file_name": "6155830.jpg"}, {"id": 6155741, "file_name": "6155741.jpg"}, {"id": 6155576, "file_name": "6155576.jpg"}, {"id": 6154802, "file_name": "6154802.jpg"}, {"id": 6154206, "file_name": "6154206.jpg"}, {"id": 6155464, "file_name": "6155464.jpg"}, {"id": 6154989, "file_name": "6154989.jpg"}, {"id": 6155193, "file_name": "6155193.jpg"}, {"id": 6153969, "file_name": "6153969.jpg"}, {"id": 6154038, "file_name": "6154038.jpg"}, {"id": 6154985, "file_name": "6154985.jpg"}, {"id": 6153323, "file_name": "6153323.jpg"}, {"id": 6155438, "file_name": "6155438.jpg"}, {"id": 6155466, "file_name": "6155466.jpg"}, {"id": 6155761, "file_name": "6155761.jpg"}, {"id": 6154979, "file_name": "6154979.jpg"}, {"id": 6155181, "file_name": "6155181.jpg"}, {"id": 6154000, "file_name": "6154000.jpg"}, {"id": 6154843, "file_name": "6154843.jpg"}, {"id": 6155196, "file_name": "6155196.jpg"}, {"id": 6155414, "file_name": "6155414.jpg"}, {"id": 6153984, "file_name": "6153984.jpg"}, {"id": 6155224, "file_name": "6155224.jpg"}, {"id": 6155223, "file_name": "6155223.jpg"}, {"id": 6154072, "file_name": "6154072.jpg"}, {"id": 6155775, "file_name": "6155775.jpg"}, {"id": 6155286, "file_name": "6155286.jpg"}, {"id": 6153632, "file_name": "6153632.jpg"}, {"id": 6155896, "file_name": "6155896.jpg"}, {"id": 6155544, "file_name": "6155544.jpg"}, {"id": 6155197, "file_name": "6155197.jpg"}, {"id": 6155505, "file_name": "6155505.jpg"}, {"id": 6154912, "file_name": "6154912.jpg"}, {"id": 6154822, "file_name": "6154822.jpg"}, {"id": 6153938, "file_name": "6153938.jpg"}, {"id": 6155462, "file_name": "6155462.jpg"}, {"id": 6156089, "file_name": "6156089.jpg"}, {"id": 6155194, "file_name": "6155194.jpg"}, {"id": 6155277, "file_name": "6155277.jpg"}, {"id": 6154960, "file_name": "6154960.jpg"}, {"id": 6155633, "file_name": "6155633.jpg"}, {"id": 6154790, "file_name": "6154790.jpg"}, {"id": 6154831, "file_name": "6154831.jpg"}, {"id": 6155221, "file_name": "6155221.jpg"}, {"id": 6155268, "file_name": "6155268.jpg"}, {"id": 6154878, "file_name": "6154878.jpg"}, {"id": 6154069, "file_name": "6154069.jpg"}, {"id": 6155637, "file_name": "6155637.jpg"}, {"id": 6155451, "file_name": "6155451.jpg"}, {"id": 6155294, "file_name": "6155294.jpg"}, {"id": 6154915, "file_name": "6154915.jpg"}, {"id": 6154974, "file_name": "6154974.jpg"}, {"id": 6154783, "file_name": "6154783.jpg"}, {"id": 6153634, "file_name": "6153634.jpg"}, {"id": 6155178, "file_name": "6155178.jpg"}, {"id": 6154914, "file_name": "6154914.jpg"}, {"id": 6155280, "file_name": "6155280.jpg"}, {"id": 6155575, "file_name": "6155575.jpg"}, {"id": 6154782, "file_name": "6154782.jpg"}, {"id": 6153492, "file_name": "6153492.jpg"}, {"id": 6154976, "file_name": "6154976.jpg"}, {"id": 6154071, "file_name": "6154071.jpg"}, {"id": 6154388, "file_name": "6154388.jpg"}, {"id": 6155216, "file_name": "6155216.jpg"}, {"id": 6154991, "file_name": "6154991.jpg"}, {"id": 6155288, "file_name": "6155288.jpg"}, {"id": 6155418, "file_name": "6155418.jpg"}, {"id": 6155895, "file_name": "6155895.jpg"}, {"id": 6155568, "file_name": "6155568.jpg"}, {"id": 6155894, "file_name": "6155894.jpg"}, {"id": 6155096, "file_name": "6155096.jpg"}, {"id": 6155498, "file_name": "6155498.jpg"}, {"id": 6154980, "file_name": "6154980.jpg"}, {"id": 6154983, "file_name": "6154983.jpg"}, {"id": 6155769, "file_name": "6155769.jpg"}, {"id": 6155180, "file_name": "6155180.jpg"}, {"id": 6155206, "file_name": "6155206.jpg"}, {"id": 6154818, "file_name": "6154818.jpg"}, {"id": 6155759, "file_name": "6155759.jpg"}, {"id": 6154962, "file_name": "6154962.jpg"}, {"id": 6154031, "file_name": "6154031.jpg"}, {"id": 6155735, "file_name": "6155735.jpg"}, {"id": 6155898, "file_name": "6155898.jpg"}, {"id": 6154788, "file_name": "6154788.jpg"}, {"id": 5994375, "file_name": "5994375.jpg"}, {"id": 5993310, "file_name": "5993310.jpg"}, {"id": 5993887, "file_name": "5993887.jpg"}, {"id": 5991919, "file_name": "5991919.jpg"}, {"id": 5991955, "file_name": "5991955.jpg"}, {"id": 5993239, "file_name": "5993239.jpg"}, {"id": 6155796, "file_name": "6155796.jpg"}, {"id": 5992069, "file_name": "5992069.jpg"}, {"id": 5991952, "file_name": "5991952.jpg"}, {"id": 5993793, "file_name": "5993793.jpg"}, {"id": 5993145, "file_name": "5993145.jpg"}, {"id": 5993213, "file_name": "5993213.jpg"}, {"id": 5993629, "file_name": "5993629.jpg"}, {"id": 5993895, "file_name": "5993895.jpg"}, {"id": 5992992, "file_name": "5992992.jpg"}, {"id": 5994191, "file_name": "5994191.jpg"}, {"id": 6153808, "file_name": "6153808.jpg"}, {"id": 5993182, "file_name": "5993182.jpg"}, {"id": 5992718, "file_name": "5992718.jpg"}, {"id": 5993477, "file_name": "5993477.jpg"}, {"id": 5993521, "file_name": "5993521.jpg"}, {"id": 5992692, "file_name": "5992692.jpg"}, {"id": 5992193, "file_name": "5992193.jpg"}, {"id": 6155834, "file_name": "6155834.jpg"}, {"id": 5994476, "file_name": "5994476.jpg"}, {"id": 5992135, "file_name": "5992135.jpg"}, {"id": 5992828, "file_name": "5992828.jpg"}, {"id": 5994320, "file_name": "5994320.jpg"}, {"id": 5993387, "file_name": "5993387.jpg"}, {"id": 5994205, "file_name": "5994205.jpg"}, {"id": 5994121, "file_name": "5994121.jpg"}, {"id": 5993482, "file_name": "5993482.jpg"}, {"id": 5993678, "file_name": "5993678.jpg"}, {"id": 5992351, "file_name": "5992351.jpg"}, {"id": 5992119, "file_name": "5992119.jpg"}, {"id": 5992222, "file_name": "5992222.jpg"}, {"id": 5991946, "file_name": "5991946.jpg"}, {"id": 5993766, "file_name": "5993766.jpg"}, {"id": 5993408, "file_name": "5993408.jpg"}, {"id": 5993666, "file_name": "5993666.jpg"}, {"id": 5992760, "file_name": "5992760.jpg"}, {"id": 5992889, "file_name": "5992889.jpg"}, {"id": 5993710, "file_name": "5993710.jpg"}, {"id": 5993178, "file_name": "5993178.jpg"}, {"id": 5992368, "file_name": "5992368.jpg"}, {"id": 5993547, "file_name": "5993547.jpg"}, {"id": 5994200, "file_name": "5994200.jpg"}, {"id": 5993875, "file_name": "5993875.jpg"}, {"id": 5994368, "file_name": "5994368.jpg"}, {"id": 5993397, "file_name": "5993397.jpg"}, {"id": 5992201, "file_name": "5992201.jpg"}, {"id": 5993587, "file_name": "5993587.jpg"}, {"id": 6154192, "file_name": "6154192.jpg"}, {"id": 5993415, "file_name": "5993415.jpg"}, {"id": 5993339, "file_name": "5993339.jpg"}, {"id": 5993411, "file_name": "5993411.jpg"}, {"id": 5993538, "file_name": "5993538.jpg"}, {"id": 5993863, "file_name": "5993863.jpg"}, {"id": 5993406, "file_name": "5993406.jpg"}, {"id": 5993158, "file_name": "5993158.jpg"}, {"id": 5992901, "file_name": "5992901.jpg"}, {"id": 5991894, "file_name": "5991894.jpg"}, {"id": 5993796, "file_name": "5993796.jpg"}, {"id": 5994434, "file_name": "5994434.jpg"}, {"id": 6155546, "file_name": "6155546.jpg"}, {"id": 5993699, "file_name": "5993699.jpg"}, {"id": 5991844, "file_name": "5991844.jpg"}, {"id": 5993331, "file_name": "5993331.jpg"}, {"id": 5993137, "file_name": "5993137.jpg"}, {"id": 5993385, "file_name": "5993385.jpg"}, {"id": 5993999, "file_name": "5993999.jpg"}, {"id": 5992058, "file_name": "5992058.jpg"}, {"id": 5993996, "file_name": "5993996.jpg"}, {"id": 5993038, "file_name": "5993038.jpg"}, {"id": 5993447, "file_name": "5993447.jpg"}, {"id": 5992854, "file_name": "5992854.jpg"}, {"id": 5992392, "file_name": "5992392.jpg"}, {"id": 5992226, "file_name": "5992226.jpg"}, {"id": 5993104, "file_name": "5993104.jpg"}, {"id": 5993490, "file_name": "5993490.jpg"}, {"id": 5992489, "file_name": "5992489.jpg"}, {"id": 5993199, "file_name": "5993199.jpg"}, {"id": 5991979, "file_name": "5991979.jpg"}, {"id": 5992247, "file_name": "5992247.jpg"}, {"id": 5993808, "file_name": "5993808.jpg"}, {"id": 5992967, "file_name": "5992967.jpg"}, {"id": 5993927, "file_name": "5993927.jpg"}, {"id": 5993129, "file_name": "5993129.jpg"}, {"id": 5994002, "file_name": "5994002.jpg"}, {"id": 5992796, "file_name": "5992796.jpg"}, {"id": 5993510, "file_name": "5993510.jpg"}, {"id": 5992175, "file_name": "5992175.jpg"}, {"id": 5993047, "file_name": "5993047.jpg"}, {"id": 5993275, "file_name": "5993275.jpg"}, {"id": 5993820, "file_name": "5993820.jpg"}, {"id": 5994207, "file_name": "5994207.jpg"}, {"id": 5992786, "file_name": "5992786.jpg"}, {"id": 5992317, "file_name": "5992317.jpg"}, {"id": 5993220, "file_name": "5993220.jpg"}, {"id": 5992592, "file_name": "5992592.jpg"}, {"id": 5992662, "file_name": "5992662.jpg"}, {"id": 6155971, "file_name": "6155971.jpg"}, {"id": 5992238, "file_name": "5992238.jpg"}, {"id": 5991980, "file_name": "5991980.jpg"}, {"id": 5992242, "file_name": "5992242.jpg"}, {"id": 5993065, "file_name": "5993065.jpg"}, {"id": 5993247, "file_name": "5993247.jpg"}, {"id": 5992363, "file_name": "5992363.jpg"}, {"id": 5993656, "file_name": "5993656.jpg"}, {"id": 5993992, "file_name": "5993992.jpg"}, {"id": 6155785, "file_name": "6155785.jpg"}, {"id": 5991752, "file_name": "5991752.jpg"}, {"id": 5992307, "file_name": "5992307.jpg"}, {"id": 5993958, "file_name": "5993958.jpg"}, {"id": 5994216, "file_name": "5994216.jpg"}, {"id": 5994418, "file_name": "5994418.jpg"}, {"id": 5993752, "file_name": "5993752.jpg"}, {"id": 5993276, "file_name": "5993276.jpg"}, {"id": 5994381, "file_name": "5994381.jpg"}, {"id": 5994061, "file_name": "5994061.jpg"}, {"id": 5993671, "file_name": "5993671.jpg"}, {"id": 5992211, "file_name": "5992211.jpg"}, {"id": 5993130, "file_name": "5993130.jpg"}, {"id": 5992998, "file_name": "5992998.jpg"}, {"id": 5992389, "file_name": "5992389.jpg"}, {"id": 5993692, "file_name": "5993692.jpg"}, {"id": 5993050, "file_name": "5993050.jpg"}, {"id": 5992353, "file_name": "5992353.jpg"}, {"id": 5993413, "file_name": "5993413.jpg"}, {"id": 6155104, "file_name": "6155104.jpg"}, {"id": 5992540, "file_name": "5992540.jpg"}, {"id": 5993704, "file_name": "5993704.jpg"}, {"id": 5993858, "file_name": "5993858.jpg"}, {"id": 5994292, "file_name": "5994292.jpg"}, {"id": 5993908, "file_name": "5993908.jpg"}, {"id": 5992002, "file_name": "5992002.jpg"}, {"id": 5993493, "file_name": "5993493.jpg"}, {"id": 6155460, "file_name": "6155460.jpg"}, {"id": 5994228, "file_name": "5994228.jpg"}, {"id": 5993412, "file_name": "5993412.jpg"}, {"id": 6156099, "file_name": "6156099.jpg"}, {"id": 5992419, "file_name": "5992419.jpg"}, {"id": 5992267, "file_name": "5992267.jpg"}, {"id": 5992477, "file_name": "5992477.jpg"}, {"id": 5992060, "file_name": "5992060.jpg"}, {"id": 5992818, "file_name": "5992818.jpg"}, {"id": 5994081, "file_name": "5994081.jpg"}, {"id": 5992420, "file_name": "5992420.jpg"}, {"id": 5992031, "file_name": "5992031.jpg"}, {"id": 5994522, "file_name": "5994522.jpg"}, {"id": 5993648, "file_name": "5993648.jpg"}, {"id": 5992294, "file_name": "5992294.jpg"}, {"id": 5991871, "file_name": "5991871.jpg"}, {"id": 5991988, "file_name": "5991988.jpg"}, {"id": 5993595, "file_name": "5993595.jpg"}, {"id": 5992957, "file_name": "5992957.jpg"}, {"id": 5992372, "file_name": "5992372.jpg"}, {"id": 5992371, "file_name": "5992371.jpg"}, {"id": 5993512, "file_name": "5993512.jpg"}, {"id": 5992648, "file_name": "5992648.jpg"}, {"id": 5993031, "file_name": "5993031.jpg"}, {"id": 5994337, "file_name": "5994337.jpg"}, {"id": 5993562, "file_name": "5993562.jpg"}, {"id": 5992923, "file_name": "5992923.jpg"}, {"id": 5992814, "file_name": "5992814.jpg"}, {"id": 5993226, "file_name": "5993226.jpg"}, {"id": 5993762, "file_name": "5993762.jpg"}, {"id": 5992173, "file_name": "5992173.jpg"}, {"id": 5992091, "file_name": "5992091.jpg"}, {"id": 6153672, "file_name": "6153672.jpg"}, {"id": 5992482, "file_name": "5992482.jpg"}, {"id": 5992342, "file_name": "5992342.jpg"}, {"id": 5994065, "file_name": "5994065.jpg"}, {"id": 5994004, "file_name": "5994004.jpg"}, {"id": 5992188, "file_name": "5992188.jpg"}, {"id": 5992965, "file_name": "5992965.jpg"}, {"id": 5991930, "file_name": "5991930.jpg"}, {"id": 5992813, "file_name": "5992813.jpg"}, {"id": 5993934, "file_name": "5993934.jpg"}, {"id": 5993809, "file_name": "5993809.jpg"}, {"id": 5994235, "file_name": "5994235.jpg"}, {"id": 5992078, "file_name": "5992078.jpg"}, {"id": 5993100, "file_name": "5993100.jpg"}, {"id": 5992463, "file_name": "5992463.jpg"}], "annotations": [{"image_id": 6154796, "category_id": 1}, {"image_id": 6154399, "category_id": 1}, {"image_id": 6153638, "category_id": 1}, {"image_id": 6155644, "category_id": 1}, {"image_id": 6155463, "category_id": 1}, {"image_id": 6154283, "category_id": 1}, {"image_id": 6155214, "category_id": 1}, {"image_id": 6155751, "category_id": 1}, {"image_id": 6154090, "category_id": 1}, {"image_id": 6154869, "category_id": 1}, {"image_id": 6154497, "category_id": 1}, {"image_id": 6155195, "category_id": 1}, {"image_id": 6155770, "category_id": 1}, {"image_id": 6153493, "category_id": 1}, {"image_id": 6155470, "category_id": 1}, {"image_id": 6154266, "category_id": 1}, {"image_id": 6155311, "category_id": 1}, {"image_id": 6153456, "category_id": 1}, {"image_id": 6155601, "category_id": 1}, {"image_id": 6156095, "category_id": 1}, {"image_id": 6155439, "category_id": 1}, {"image_id": 6155176, "category_id": 1}, {"image_id": 6155298, "category_id": 1}, {"image_id": 6155303, "category_id": 1}, {"image_id": 6155008, "category_id": 1}, {"image_id": 6155632, "category_id": 1}, {"image_id": 6155744, "category_id": 1}, {"image_id": 6155747, "category_id": 1}, {"image_id": 6155450, "category_id": 1}, {"image_id": 6154795, "category_id": 1}, {"image_id": 6154841, "category_id": 1}, {"image_id": 6155960, "category_id": 1}, {"image_id": 6155434, "category_id": 1}, {"image_id": 6153637, "category_id": 1}, {"image_id": 6155111, "category_id": 1}, {"image_id": 6155179, "category_id": 1}, {"image_id": 6155425, "category_id": 1}, {"image_id": 6154195, "category_id": 1}, {"image_id": 6155410, "category_id": 1}, {"image_id": 6155189, "category_id": 1}, {"image_id": 6155321, "category_id": 1}, {"image_id": 6155448, "category_id": 1}, {"image_id": 6155264, "category_id": 1}, {"image_id": 6155203, "category_id": 1}, {"image_id": 6155599, "category_id": 1}, {"image_id": 6155204, "category_id": 1}, {"image_id": 6155205, "category_id": 1}, {"image_id": 6155157, "category_id": 1}, {"image_id": 6155740, "category_id": 1}, {"image_id": 6154927, "category_id": 1}, {"image_id": 6154936, "category_id": 1}, {"image_id": 6155771, "category_id": 1}, {"image_id": 6155443, "category_id": 1}, {"image_id": 6154820, "category_id": 1}, {"image_id": 6155000, "category_id": 1}, {"image_id": 6154972, "category_id": 1}, {"image_id": 6155743, "category_id": 1}, {"image_id": 6155738, "category_id": 1}, {"image_id": 6153631, "category_id": 1}, {"image_id": 6154940, "category_id": 1}, {"image_id": 6154077, "category_id": 1}, {"image_id": 6153635, "category_id": 1}, {"image_id": 6154805, "category_id": 1}, {"image_id": 6153696, "category_id": 1}, {"image_id": 6154390, "category_id": 1}, {"image_id": 6154898, "category_id": 1}, {"image_id": 6155198, "category_id": 1}, {"image_id": 6155619, "category_id": 1}, {"image_id": 6154975, "category_id": 1}, {"image_id": 6154806, "category_id": 1}, {"image_id": 6155184, "category_id": 1}, {"image_id": 6154032, "category_id": 1}, {"image_id": 6155469, "category_id": 1}, {"image_id": 6153572, "category_id": 1}, {"image_id": 6155772, "category_id": 1}, {"image_id": 6155803, "category_id": 1}, {"image_id": 6153491, "category_id": 1}, {"image_id": 6154078, "category_id": 1}, {"image_id": 6155291, "category_id": 1}, {"image_id": 6154981, "category_id": 1}, {"image_id": 6155183, "category_id": 1}, {"image_id": 6156063, "category_id": 1}, {"image_id": 6154961, "category_id": 1}, {"image_id": 6155435, "category_id": 1}, {"image_id": 6155442, "category_id": 1}, {"image_id": 6155292, "category_id": 1}, {"image_id": 6155207, "category_id": 1}, {"image_id": 6154959, "category_id": 1}, {"image_id": 6154398, "category_id": 1}, {"image_id": 6154384, "category_id": 1}, {"image_id": 6155312, "category_id": 1}, {"image_id": 6155208, "category_id": 1}, {"image_id": 6155246, "category_id": 1}, {"image_id": 6155003, "category_id": 1}, {"image_id": 6155753, "category_id": 1}, {"image_id": 6154817, "category_id": 1}, {"image_id": 6154803, "category_id": 1}, {"image_id": 6155653, "category_id": 1}, {"image_id": 6154194, "category_id": 1}, {"image_id": 6155155, "category_id": 1}, {"image_id": 6155830, "category_id": 1}, {"image_id": 6155741, "category_id": 1}, {"image_id": 6155576, "category_id": 1}, {"image_id": 6154802, "category_id": 1}, {"image_id": 6154206, "category_id": 1}, {"image_id": 6155464, "category_id": 1}, {"image_id": 6154989, "category_id": 1}, {"image_id": 6155193, "category_id": 1}, {"image_id": 6153969, "category_id": 1}, {"image_id": 6154038, "category_id": 1}, {"image_id": 6154985, "category_id": 1}, {"image_id": 6153323, "category_id": 1}, {"image_id": 6155438, "category_id": 1}, {"image_id": 6155466, "category_id": 1}, {"image_id": 6155761, "category_id": 1}, {"image_id": 6154979, "category_id": 1}, {"image_id": 6155181, "category_id": 1}, {"image_id": 6154000, "category_id": 1}, {"image_id": 6154843, "category_id": 1}, {"image_id": 6155196, "category_id": 1}, {"image_id": 6155414, "category_id": 1}, {"image_id": 6153984, "category_id": 1}, {"image_id": 6155224, "category_id": 1}, {"image_id": 6155223, "category_id": 1}, {"image_id": 6154072, "category_id": 1}, {"image_id": 6155775, "category_id": 1}, {"image_id": 6155286, "category_id": 1}, {"image_id": 6153632, "category_id": 1}, {"image_id": 6155896, "category_id": 1}, {"image_id": 6155544, "category_id": 1}, {"image_id": 6155197, "category_id": 1}, {"image_id": 6155505, "category_id": 1}, {"image_id": 6154912, "category_id": 1}, {"image_id": 6154822, "category_id": 1}, {"image_id": 6153938, "category_id": 1}, {"image_id": 6155462, "category_id": 1}, {"image_id": 6156089, "category_id": 1}, {"image_id": 6155194, "category_id": 1}, {"image_id": 6155277, "category_id": 1}, {"image_id": 6154960, "category_id": 1}, {"image_id": 6155633, "category_id": 1}, {"image_id": 6154790, "category_id": 1}, {"image_id": 6154831, "category_id": 1}, {"image_id": 6155221, "category_id": 1}, {"image_id": 6155268, "category_id": 1}, {"image_id": 6154878, "category_id": 1}, {"image_id": 6154069, "category_id": 1}, {"image_id": 6155637, "category_id": 1}, {"image_id": 6155451, "category_id": 1}, {"image_id": 6155294, "category_id": 1}, {"image_id": 6154915, "category_id": 1}, {"image_id": 6154974, "category_id": 1}, {"image_id": 6154783, "category_id": 1}, {"image_id": 6153634, "category_id": 1}, {"image_id": 6155178, "category_id": 1}, {"image_id": 6154914, "category_id": 1}, {"image_id": 6155280, "category_id": 1}, {"image_id": 6155575, "category_id": 1}, {"image_id": 6154782, "category_id": 1}, {"image_id": 6153492, "category_id": 1}, {"image_id": 6154976, "category_id": 1}, {"image_id": 6154071, "category_id": 1}, {"image_id": 6154388, "category_id": 1}, {"image_id": 6155216, "category_id": 1}, {"image_id": 6154991, "category_id": 1}, {"image_id": 6155288, "category_id": 1}, {"image_id": 6155418, "category_id": 1}, {"image_id": 6155895, "category_id": 1}, {"image_id": 6155568, "category_id": 1}, {"image_id": 6155894, "category_id": 1}, {"image_id": 6155096, "category_id": 1}, {"image_id": 6155498, "category_id": 1}, {"image_id": 6154980, "category_id": 1}, {"image_id": 6154983, "category_id": 1}, {"image_id": 6155769, "category_id": 1}, {"image_id": 6155180, "category_id": 1}, {"image_id": 6155206, "category_id": 1}, {"image_id": 6154818, "category_id": 1}, {"image_id": 6155759, "category_id": 1}, {"image_id": 6154962, "category_id": 1}, {"image_id": 6154031, "category_id": 1}, {"image_id": 6155735, "category_id": 1}, {"image_id": 6155898, "category_id": 1}, {"image_id": 6154788, "category_id": 1}, {"image_id": 5994375, "category_id": 0}, {"image_id": 5993310, "category_id": 0}, {"image_id": 5993887, "category_id": 0}, {"image_id": 5991919, "category_id": 0}, {"image_id": 5991955, "category_id": 0}, {"image_id": 5993239, "category_id": 0}, {"image_id": 6155796, "category_id": 0}, {"image_id": 5992069, "category_id": 0}, {"image_id": 5991952, "category_id": 0}, {"image_id": 5993793, "category_id": 0}, {"image_id": 5993145, "category_id": 0}, {"image_id": 5993213, "category_id": 0}, {"image_id": 5993629, "category_id": 0}, {"image_id": 5993895, "category_id": 0}, {"image_id": 5992992, "category_id": 0}, {"image_id": 5994191, "category_id": 0}, {"image_id": 6153808, "category_id": 0}, {"image_id": 5993182, "category_id": 0}, {"image_id": 5992718, "category_id": 0}, {"image_id": 5993477, "category_id": 0}, {"image_id": 5993521, "category_id": 0}, {"image_id": 5992692, "category_id": 0}, {"image_id": 5992193, "category_id": 0}, {"image_id": 6155834, "category_id": 0}, {"image_id": 5994476, "category_id": 0}, {"image_id": 5992135, "category_id": 0}, {"image_id": 5992828, "category_id": 0}, {"image_id": 5994320, "category_id": 0}, {"image_id": 5993387, "category_id": 0}, {"image_id": 5994205, "category_id": 0}, {"image_id": 5994121, "category_id": 0}, {"image_id": 5993482, "category_id": 0}, {"image_id": 5993678, "category_id": 0}, {"image_id": 5992351, "category_id": 0}, {"image_id": 5992119, "category_id": 0}, {"image_id": 5992222, "category_id": 0}, {"image_id": 5991946, "category_id": 0}, {"image_id": 5993766, "category_id": 0}, {"image_id": 5993408, "category_id": 0}, {"image_id": 5993666, "category_id": 0}, {"image_id": 5992760, "category_id": 0}, {"image_id": 5992889, "category_id": 0}, {"image_id": 5993710, "category_id": 0}, {"image_id": 5993178, "category_id": 0}, {"image_id": 5992368, "category_id": 0}, {"image_id": 5993547, "category_id": 0}, {"image_id": 5994200, "category_id": 0}, {"image_id": 5993875, "category_id": 0}, {"image_id": 5994368, "category_id": 0}, {"image_id": 5993397, "category_id": 0}, {"image_id": 5992201, "category_id": 0}, {"image_id": 5993587, "category_id": 0}, {"image_id": 6154192, "category_id": 0}, {"image_id": 5993415, "category_id": 0}, {"image_id": 5993339, "category_id": 0}, {"image_id": 5993411, "category_id": 0}, {"image_id": 5993538, "category_id": 0}, {"image_id": 5993863, "category_id": 0}, {"image_id": 5993406, "category_id": 0}, {"image_id": 5993158, "category_id": 0}, {"image_id": 5992901, "category_id": 0}, {"image_id": 5991894, "category_id": 0}, {"image_id": 5993796, "category_id": 0}, {"image_id": 5994434, "category_id": 0}, {"image_id": 6155546, "category_id": 0}, {"image_id": 5993699, "category_id": 0}, {"image_id": 5991844, "category_id": 0}, {"image_id": 5993331, "category_id": 0}, {"image_id": 5993137, "category_id": 0}, {"image_id": 5993385, "category_id": 0}, {"image_id": 5993999, "category_id": 0}, {"image_id": 5992058, "category_id": 0}, {"image_id": 5993996, "category_id": 0}, {"image_id": 5993038, "category_id": 0}, {"image_id": 5993447, "category_id": 0}, {"image_id": 5992854, "category_id": 0}, {"image_id": 5992392, "category_id": 0}, {"image_id": 5992226, "category_id": 0}, {"image_id": 5993104, "category_id": 0}, {"image_id": 5993490, "category_id": 0}, {"image_id": 5992489, "category_id": 0}, {"image_id": 5993199, "category_id": 0}, {"image_id": 5991979, "category_id": 0}, {"image_id": 5992247, "category_id": 0}, {"image_id": 5993808, "category_id": 0}, {"image_id": 5992967, "category_id": 0}, {"image_id": 5993927, "category_id": 0}, {"image_id": 5993129, "category_id": 0}, {"image_id": 5994002, "category_id": 0}, {"image_id": 5992796, "category_id": 0}, {"image_id": 5993510, "category_id": 0}, {"image_id": 5992175, "category_id": 0}, {"image_id": 5993047, "category_id": 0}, {"image_id": 5993275, "category_id": 0}, {"image_id": 5993820, "category_id": 0}, {"image_id": 5994207, "category_id": 0}, {"image_id": 5992786, "category_id": 0}, {"image_id": 5992317, "category_id": 0}, {"image_id": 5993220, "category_id": 0}, {"image_id": 5992592, "category_id": 0}, {"image_id": 5992662, "category_id": 0}, {"image_id": 6155971, "category_id": 0}, {"image_id": 5992238, "category_id": 0}, {"image_id": 5991980, "category_id": 0}, {"image_id": 5992242, "category_id": 0}, {"image_id": 5993065, "category_id": 0}, {"image_id": 5993247, "category_id": 0}, {"image_id": 5992363, "category_id": 0}, {"image_id": 5993656, "category_id": 0}, {"image_id": 5993992, "category_id": 0}, {"image_id": 6155785, "category_id": 0}, {"image_id": 5991752, "category_id": 0}, {"image_id": 5992307, "category_id": 0}, {"image_id": 5993958, "category_id": 0}, {"image_id": 5994216, "category_id": 0}, {"image_id": 5994418, "category_id": 0}, {"image_id": 5993752, "category_id": 0}, {"image_id": 5993276, "category_id": 0}, {"image_id": 5994381, "category_id": 0}, {"image_id": 5994061, "category_id": 0}, {"image_id": 5993671, "category_id": 0}, {"image_id": 5992211, "category_id": 0}, {"image_id": 5993130, "category_id": 0}, {"image_id": 5992998, "category_id": 0}, {"image_id": 5992389, "category_id": 0}, {"image_id": 5993692, "category_id": 0}, {"image_id": 5993050, "category_id": 0}, {"image_id": 5992353, "category_id": 0}, {"image_id": 5993413, "category_id": 0}, {"image_id": 6155104, "category_id": 0}, {"image_id": 5992540, "category_id": 0}, {"image_id": 5993704, "category_id": 0}, {"image_id": 5993858, "category_id": 0}, {"image_id": 5994292, "category_id": 0}, {"image_id": 5993908, "category_id": 0}, {"image_id": 5992002, "category_id": 0}, {"image_id": 5993493, "category_id": 0}, {"image_id": 6155460, "category_id": 0}, {"image_id": 5994228, "category_id": 0}, {"image_id": 5993412, "category_id": 0}, {"image_id": 6156099, "category_id": 0}, {"image_id": 5992419, "category_id": 0}, {"image_id": 5992267, "category_id": 0}, {"image_id": 5992477, "category_id": 0}, {"image_id": 5992060, "category_id": 0}, {"image_id": 5992818, "category_id": 0}, {"image_id": 5994081, "category_id": 0}, {"image_id": 5992420, "category_id": 0}, {"image_id": 5992031, "category_id": 0}, {"image_id": 5994522, "category_id": 0}, {"image_id": 5993648, "category_id": 0}, {"image_id": 5992294, "category_id": 0}, {"image_id": 5991871, "category_id": 0}, {"image_id": 5991988, "category_id": 0}, {"image_id": 5993595, "category_id": 0}, {"image_id": 5992957, "category_id": 0}, {"image_id": 5992372, "category_id": 0}, {"image_id": 5992371, "category_id": 0}, {"image_id": 5993512, "category_id": 0}, {"image_id": 5992648, "category_id": 0}, {"image_id": 5993031, "category_id": 0}, {"image_id": 5994337, "category_id": 0}, {"image_id": 5993562, "category_id": 0}, {"image_id": 5992923, "category_id": 0}, {"image_id": 5992814, "category_id": 0}, {"image_id": 5993226, "category_id": 0}, {"image_id": 5993762, "category_id": 0}, {"image_id": 5992173, "category_id": 0}, {"image_id": 5992091, "category_id": 0}, {"image_id": 6153672, "category_id": 0}, {"image_id": 5992482, "category_id": 0}, {"image_id": 5992342, "category_id": 0}, {"image_id": 5994065, "category_id": 0}, {"image_id": 5994004, "category_id": 0}, {"image_id": 5992188, "category_id": 0}, {"image_id": 5992965, "category_id": 0}, {"image_id": 5991930, "category_id": 0}, {"image_id": 5992813, "category_id": 0}, {"image_id": 5993934, "category_id": 0}, {"image_id": 5993809, "category_id": 0}, {"image_id": 5994235, "category_id": 0}, {"image_id": 5992078, "category_id": 0}, {"image_id": 5993100, "category_id": 0}, {"image_id": 5992463, "category_id": 0}], "categories": [{"id": 1, "name": "ff"}, {"id": 2, "name": "empty"}]}